noteflow/__init__.py
noteflow/noteflow.py
noteflow/fonts/hack-bold-webfont.ttf
noteflow/fonts/hack-bold-webfont.woff
noteflow/fonts/hack-bold-webfont.woff2
noteflow/fonts/hack-bolditalic-webfont.ttf
noteflow/fonts/hack-bolditalic-webfont.woff
noteflow/fonts/hack-bolditalic-webfont.woff2
noteflow/fonts/hack-italic-webfont.ttf
noteflow/fonts/hack-italic-webfont.woff
noteflow/fonts/hack-italic-webfont.woff2
noteflow/fonts/hack-regular-webfont.ttf
noteflow/fonts/hack-regular-webfont.woff
noteflow/fonts/hack-regular-webfont.woff2
noteflow/fonts/spacemono-bold-webfont.ttf
noteflow/fonts/spacemono-bold-webfont.woff
noteflow/fonts/spacemono-bold-webfont.woff2
noteflow/fonts/spacemono-bolditalic-webfont.ttf
noteflow/fonts/spacemono-bolditalic-webfont.woff
noteflow/fonts/spacemono-bolditalic-webfont.woff2
noteflow/fonts/spacemono-italic-webfont.ttf
noteflow/fonts/spacemono-italic-webfont.woff
noteflow/fonts/spacemono-italic-webfont.woff2
noteflow/fonts/spacemono-regular-webfont.ttf
noteflow/fonts/spacemono-regular-webfont.woff
noteflow/fonts/spacemono-regular-webfont.woff2
noteflow/fonts/stylesheet.css
noteflow/static/favicon.ico
noteflow-0.3.1.dist-info/LICENSE
noteflow-0.3.1.dist-info/METADATA
noteflow-0.3.1.dist-info/WHEEL
noteflow-0.3.1.dist-info/entry_points.txt
noteflow-0.3.1.dist-info/top_level.txt
noteflow-0.3.1.dist-info/RECORD
