Metadata-Version: 2.1
Name: noteflow
Version: 0.3.1
Summary: A lightweight, Markdown-based note-taking application with task management capabilities, providing a clean interface for creating, viewing, and managing notes with support for tasks, images, and code snippets.
Author-email: Xafloc <xafloc@tetrago.com>
Project-URL: Homepage, https://github.com/Xafloc/NoteFlow
Project-URL: Bug Tracker, https://github.com/Xafloc/NoteFlow/issues
Classifier: Programming Language :: Python :: 3.9
Classifier: License :: OSI Approved :: GNU General Public License v3 (GPLv3)
Classifier: Operating System :: OS Independent
Classifier: Environment :: Web Environment
Classifier: Framework :: FastAPI
Classifier: Topic :: Office/Business :: News/Diary
Classifier: Topic :: Text Processing :: Markup :: Markdown
Classifier: Topic :: Utilities
Requires-Python: >=3.9
License-File: LICENSE
Requires-Dist: fastapi >=0.104.1
Requires-Dist: uvicorn >=0.24.0
Requires-Dist: markdown-it-py >=3.0.0
Requires-Dist: mdit-py-plugins >=0.3.1
Requires-Dist: python-multipart >=0.0.6
Requires-Dist: pydantic >=2.4.2
Requires-Dist: jinja2 >=3.1.2
Requires-Dist: requests >=2.31.0
Requires-Dist: beautifulsoup4 >=4.12.0
Requires-Dist: platformdirs >=3.0.0
Requires-Dist: psutil >=5.9.5
